doris_vector_search/__init__.py
doris_vector_search/test_multipthread_conn.py
doris_vector_search/test_multithread_sdk.py
doris_vector_search/test_upload.py
doris_vector_search-0.0.9.dist-info/METADATA
doris_vector_search-0.0.9.dist-info/WHEEL
doris_vector_search-0.0.9.dist-info/top_level.txt
doris_vector_search-0.0.9.dist-info/RECORD
