Metadata-Version: 2.4
Name: doris-vector-search
Version: 0.0.9
Summary: Doris Vector Search Python SDK
Requires-Python: >=3.8
Requires-Dist: mysql-connector
Provides-Extra: dev
Requires-Dist: pre-commit; extra == "dev"
